{
    "hyperparameters": {
        "batch_size": 24,
        "channels": 1,
        "cropping_position": [40, 10],
        "decay": 0.01,
        "do_cropping": false,
        "epochs": 1,
        "learning_rate": 0.01,
        "mean": 0,
        "momentum": 0.9,
        "patience": 10,
        "use_mean": false
    },

    "data_input_directory":"../data/ep_intensity",
    "output_path": "../results/training",
    
    "checkpointing_path": "../checkpoints",
    "checkpointing_title": "checkpointing_test",

    "shuffle_the_folds": true,
    "rotations": "all",
    "seed": 9,

    "class_names": ["fat", "ligament", "flavum", "epidural space", "spinal cord"],
    "selected_model_name": "InceptionV3",
    "subject_list": ["e1", "e2", "e3", "e4", "e5", "e6"],
    "test_subjects": ["e1", "e2"],

    "image_size": [800, 400],
	"target_height": 241,
    "target_width": 181
}




